setup.py
pyoa/__init__.py
pyoa/ara.py
pyoa/aravars.py
pyoa/sys.py
pyoa.egg-info/PKG-INFO
pyoa.egg-info/SOURCES.txt
pyoa.egg-info/dependency_links.txt
pyoa.egg-info/not-zip-safe
pyoa.egg-info/top_level.txt