Metadata-Version: 1.0
Name: pyoa
Version: 0.115
Summary: A set of functions for processing and analyzing classical Arabic texts in OpenArabic
Home-page: http://github.com/openarabic/pyoa
Author: Maxim Romanov
Author-email: maxim.romanov@uni-leipzig.de
License: MIT
Platform: UNKNOWN
